{
  "movies": [
    {
      "id": 1,
      "title": "Inception",
      "genre": "Sci-Fi",
      "director": "Christopher Nolan",
      "year": 2010,
      "poster": "https://image.tmdb.org/t/p/w500/9gk7adHYeDvHkCSEqAvQNLV5Uge.jpg",
      "status": "watched",
      "rating": 9,
      "review": "A mind-bending masterpiece. The layered dream sequences are brilliantly executed.",
      "priority": "high",
      "watchedOn": "2024-01-15",
      "addedOn": "2024-01-10"
    },
    {
      "id": 2,
      "title": "The Dark Knight",
      "genre": "Action",
      "director": "Christopher Nolan",
      "year": 2008,
      "poster": "https://image.tmdb.org/t/p/w500/qJ2tW6WMUDux911r6m7haRef0WH.jpg",
      "status": "watched",
      "rating": 10,
      "review": "Ledger's Joker is the greatest villain performance in cinema history.",
      "priority": "high",
      "watchedOn": "2024-01-20",
      "addedOn": "2024-01-10"
    },
    {
      "id": 3,
      "title": "Interstellar",
      "genre": "Sci-Fi",
      "director": "Christopher Nolan",
      "year": 2014,
      "poster": "https://image.tmdb.org/t/p/w500/gEU2QniE6E77NI6lCU6MxlNBvIx.jpg",
      "status": "watched",
      "rating": 9,
      "review": "Emotionally overwhelming. The docking scene and organ score are unforgettable.",
      "priority": "high",
      "watchedOn": "2024-02-01",
      "addedOn": "2024-01-12"
    },
    {
      "id": 4,
      "title": "Parasite",
      "genre": "Thriller",
      "director": "Bong Joon-ho",
      "year": 2019,
      "poster": "https://image.tmdb.org/t/p/w500/7IiTTgloJzvGI1TAYymCfbfl3vT.jpg",
      "status": "watched",
      "rating": 8,
      "review": "A flawless social thriller. The genre shifts are handled with surgical precision.",
      "priority": "medium",
      "watchedOn": "2024-02-10",
      "addedOn": "2024-01-18"
    },
    {
      "id": 5,
      "title": "Dune: Part Two",
      "genre": "Sci-Fi",
      "director": "Denis Villeneuve",
      "year": 2024,
      "poster": "https://image.tmdb.org/t/p/w500/8b8R8l88Qje9dn9OE8PY05Nxl1X.jpg",
      "status": "watchlist",
      "rating": null,
      "review": "",
      "priority": "high",
      "watchedOn": null,
      "addedOn": "2024-03-01"
    },
    {
      "id": 6,
      "title": "Oppenheimer",
      "genre": "Drama",
      "director": "Christopher Nolan",
      "year": 2023,
      "poster": "https://image.tmdb.org/t/p/w500/8Gxv8gSFCU0XGDykEGv7zR1n2ua.jpg",
      "status": "watched",
      "rating": 8,
      "review": "A towering achievement. The Trinity scene is pure cinematic terror.",
      "priority": "high",
      "watchedOn": "2024-02-20",
      "addedOn": "2024-01-20"
    },
    {
      "id": 7,
      "title": "Poor Things",
      "genre": "Drama",
      "director": "Yorgos Lanthimos",
      "year": 2023,
      "poster": "https://image.tmdb.org/t/p/w500/kCGlIMHnOm8JPXIwCKuGwXh4CFo.jpg",
      "status": "watchlist",
      "rating": null,
      "review": "",
      "priority": "medium",
      "watchedOn": null,
      "addedOn": "2024-02-25"
    },
    {
      "id": 8,
      "title": "The Holdovers",
      "genre": "Drama",
      "director": "Alexander Payne",
      "year": 2023,
      "poster": "https://image.tmdb.org/t/p/w500/VHSzNBTwxV8vh7wylo7O5t3xBAV.jpg",
      "status": "watchlist",
      "rating": null,
      "review": "",
      "priority": "low",
      "watchedOn": null,
      "addedOn": "2024-03-05"
    },
    {
      "id": 9,
      "title": "Past Lives",
      "genre": "Romance",
      "director": "Celine Song",
      "year": 2023,
      "poster": "https://image.tmdb.org/t/p/w500/k3waqVXSnYLTNMu7LbFRy8oGCBi.jpg",
      "status": "watched",
      "rating": 9,
      "review": "Quietly devastating. The ending lingers for days.",
      "priority": "high",
      "watchedOn": "2024-03-10",
      "addedOn": "2024-02-28"
    },
    {
      "id": 10,
      "title": "Mad Max: Fury Road",
      "genre": "Action",
      "director": "George Miller",
      "year": 2015,
      "poster": "https://image.tmdb.org/t/p/w500/8tZYtuWezp8JbcsvHYO0O46tFbo.jpg",
      "status": "watched",
      "rating": 9,
      "review": "Two hours of relentless, operatic action. A new genre benchmark.",
      "priority": "medium",
      "watchedOn": "2024-01-28",
      "addedOn": "2024-01-15"
    },
    {
      "title": "Asur: Welcome to Your Dark Side",
      "genre": "Crime",
      "director": "",
      "year": 2020,
      "poster": "https://m.media-amazon.com/images/M/MV5BMDZkOGQzMjItNTliOC00NTIxLTg4ODEtNTMxZWY1OTk5ZWM0XkEyXkFqcGc@._V1_SX300.jpg",
      "mediaType": "series",
      "status": "watchlist",
      "priority": "high",
      "rating": null,
      "review": "",
      "watchedOn": null,
      "addedOn": "2026-03-11",
      "id": 11
    },
    {
      "title": "The First Frost",
      "genre": "Drama",
      "director": "",
      "year": 2025,
      "poster": "https://m.media-amazon.com/images/M/MV5BNGRhZjkxNmMtMGI0Ny00N2M1LTkzM2ItNzg2YWIwYjcwNzE0XkEyXkFqcGc@._V1_SX300.jpg",
      "mediaType": "series",
      "status": "watchlist",
      "priority": "medium",
      "rating": null,
      "review": "",
      "watchedOn": null,
      "addedOn": "2026-03-12",
      "id": 12
    }
  ]
}